oneat/__init__.py
oneat/_version.py
oneat/caped.yaml
oneat/pretrained.py
oneat/NEATModels/.neat_focus.py.swp
oneat/NEATModels/Staticconfig.py
oneat/NEATModels/TrainConfig.py
oneat/NEATModels/__init__.py
oneat/NEATModels/config.py
oneat/NEATModels/loss.py
oneat/NEATModels/neat_densesurfacenet.py
oneat/NEATModels/neat_densevollnet.py
oneat/NEATModels/neat_dynamic_resnet.py
oneat/NEATModels/neat_focus.py
oneat/NEATModels/neat_focus_microscope.py
oneat/NEATModels/neat_lstm.py
oneat/NEATModels/neat_microscope.py
oneat/NEATModels/neat_vollnet.py
oneat/NEATModels/nets.py
oneat/NEATUtils/HolovizNapari.py
oneat/NEATUtils/MovieCreator.py
oneat/NEATUtils/NMS.py
oneat/NEATUtils/TrainDataMaker.py
oneat/NEATUtils/TrainDataMakerYolo.py
oneat/NEATUtils/VisualizeDetections.py
oneat/NEATUtils/Zmapgen.py
oneat/NEATUtils/__init__.py
oneat/NEATUtils/plotters.py
oneat/NEATUtils/utils.py
oneat/NEATUtils/oneat_animation/OneatScoreKeeper.py
oneat/NEATUtils/oneat_animation/OneatSimpleVisualization.py
oneat/NEATUtils/oneat_animation/OneatVisualization.py
oneat/NEATUtils/oneat_animation/OneatVolumeVisualization.py
oneat/NEATUtils/oneat_animation/__init__.py
oneat/NEATUtils/oneat_animation/_qt/OneatFrameWidget.py
oneat/NEATUtils/oneat_animation/_qt/OneatVisWidget.py
oneat/NEATUtils/oneat_animation/_qt/__init__.py
oneat/NEATUtils/oneat_animation/_qt/oneat_visualize_widget.py
oneat/NEATUtils/oneat_animation/_qt/oneat_volume_widget.py
oneat/NEATUtils/oneat_animation/_qt/oneat_widget.py
oneat/_tests/__init__.py
oneat/_tests/test_nets.py
oneat/_tests/utils.py
oneat/_tests/variables/variables.data-00000-of-00001
oneat/_tests/variables/variables.index
oneat-6.9.9.dist-info/licenses/LICENSE
oneat-6.9.9.dist-info/METADATA
oneat-6.9.9.dist-info/WHEEL
oneat-6.9.9.dist-info/entry_points.txt
oneat-6.9.9.dist-info/top_level.txt
oneat-6.9.9.dist-info/RECORD
