Metadata-Version: 2.4
Name: oneat
Version: 6.9.9
Summary: Action classification for TZYX/TYX shaped images, Static classification for TYX/YX shaped images
Home-page: https://github.com/Kapoorlabs-CAPED/caped-ai-oneat
Author: Varun Kapoor
Author-email: randomaccessiblekapoor@gmail.com
License: BSD-3-Clause
Project-URL: Bug Tracker, https://github.com/Kapoorlabs-CAPED/caped-ai-oneat/issues
Project-URL: Documentation, https://github.com/Kapoorlabs-CAPED/caped-ai-oneat#README.md
Project-URL: Source Code, https://github.com/Kapoorlabs-CAPED/caped-ai-oneat
Project-URL: User Support, https://github.com/Kapoorlabs-CAPED/caped-ai-oneat/issues
Classifier: Development Status :: 5 - Production/Stable
Classifier: Intended Audience :: Developers
Classifier: License :: OSI Approved :: BSD License
Classifier: Operating System :: OS Independent
Classifier: Programming Language :: Python
Classifier: Programming Language :: Python :: 3
Classifier: Programming Language :: Python :: 3 :: Only
Classifier: Programming Language :: Python :: 3.8
Classifier: Programming Language :: Python :: 3.9
Classifier: Programming Language :: Python :: 3.10
Classifier: Topic :: Scientific/Engineering :: Image Processing
Requires-Python: >=3.8
License-File: LICENSE
Requires-Dist: pandas
Requires-Dist: vollseg-napari
Requires-Dist: scipy
Requires-Dist: tifffile
Requires-Dist: matplotlib
Requires-Dist: imagecodecs
Requires-Dist: scikit-learn
Requires-Dist: dask
Requires-Dist: natsort
Requires-Dist: napari-animation
Requires-Dist: pydot
Requires-Dist: graphviz
Requires-Dist: hydra-core
Requires-Dist: caped-ai-metrics
Requires-Dist: seaborn
Provides-Extra: testing
Requires-Dist: tox; extra == "testing"
Requires-Dist: pytest; extra == "testing"
Requires-Dist: pytest-cov; extra == "testing"
Dynamic: license-file
